{
  "prefix": "130.137.136.0/24",
  "event_type": "C",
  "type_name": "\u8def\u7531\u632f\u8361",
  "origin_as": 0,
  "start_time": 1767632539.390614,
  "end_time": 1767633704.365959,
  "duration_sec": 1164.9753448963165,
  "duration_str": "19\u5206\u949f",
  "total_peers": 16,
  "max_withdrawn": 16,
  "total_w": 21,
  "total_a": 96,
  "close_reason": "\u8def\u7531\u632f\u8361: 21W/96A",
  "w_peers": [
    293,
    1403,
    2152,
    2497,
    2914,
    3130,
    3257,
    3549,
    3741,
    6939,
    7018,
    20130,
    22652,
    37100,
    57463,
    57866
  ],
  "a_peers": [
    293,
    1403,
    2152,
    2497,
    2914,
    3130,
    3257,
    3549,
    3741,
    6939,
    7018,
    20130,
    22652,
    37100,
    57463,
    57866
  ],
  "w_count": 21,
  "a_count": 96,
  "withdrawal_spread_sec": 0,
  "recovery_spread_sec": 0,
  "topology": [],
  "updates": [
    {
      "ts": 1767632539.390614,
      "type": "A",
      "peer_as": 57463,
      "as_path": "57463 16509"
    },
    {
      "ts": 1767632539.44151,
      "type": "A",
      "peer_as": 57866,
      "as_path": "57866 5511 16509"
    },
    {
      "ts": 1767632540.035954,
      "type": "A",
      "peer_as": 57866,
      "as_path": "57866 6830 16509"
    },
    {
      "ts": 1767632540.206095,
      "type": "W",
      "peer_as": 57463,
      "as_path": ""
    },
    {
      "ts": 1767632540.262172,
      "type": "W",
      "peer_as": 3257,
      "as_path": ""
    },
    {
      "ts": 1767632540.456571,
      "type": "A",
      "peer_as": 3257,
      "as_path": "3257 2914 16509"
    },
    {
      "ts": 1767632540.45672,
      "type": "A",
      "peer_as": 3257,
      "as_path": "3257 6453 16509"
    },
    {
      "ts": 1767632541.160316,
      "type": "A",
      "peer_as": 37100,
      "as_path": "37100 6453 16509"
    },
    {
      "ts": 1767632541.160377,
      "type": "A",
      "peer_as": 37100,
      "as_path": "37100 6762 16509"
    },
    {
      "ts": 1767632541.711075,
      "type": "A",
      "peer_as": 2914,
      "as_path": "2914 6453 16509"
    },
    {
      "ts": 1767632542.108461,
      "type": "W",
      "peer_as": 6939,
      "as_path": ""
    },
    {
      "ts": 1767632542.164545,
      "type": "A",
      "peer_as": 6939,
      "as_path": "6939 1299 16509"
    },
    {
      "ts": 1767632542.197611,
      "type": "A",
      "peer_as": 20130,
      "as_path": "20130 6939 1299 16509"
    },
    {
      "ts": 1767632542.784642,
      "type": "A",
      "peer_as": 37100,
      "as_path": "37100 6453 16509"
    },
    {
      "ts": 1767632543.729041,
      "type": "A",
      "peer_as": 2914,
      "as_path": "2914 6453 16509"
    },
    {
      "ts": 1767632544.236742,
      "type": "A",
      "peer_as": 3130,
      "as_path": "3130 174 1299 16509"
    },
    {
      "ts": 1767632544.909315,
      "type": "A",
      "peer_as": 22652,
      "as_path": "22652 1299 16509"
    },
    {
      "ts": 1767632545.869014,
      "type": "A",
      "peer_as": 2914,
      "as_path": "2914 6453 16509"
    },
    {
      "ts": 1767632549.47028,
      "type": "A",
      "peer_as": 3257,
      "as_path": "3257 174 16509"
    },
    {
      "ts": 1767632551.212261,
      "type": "A",
      "peer_as": 7018,
      "as_path": "7018 6453 16509"
    },
    {
      "ts": 1767632551.3729,
      "type": "A",
      "peer_as": 1403,
      "as_path": "1403 6461 16509"
    },
    {
      "ts": 1767632551.412967,
      "type": "A",
      "peer_as": 7018,
      "as_path": "7018 1299 16509"
    },
    {
      "ts": 1767632551.555138,
      "type": "A",
      "peer_as": 2152,
      "as_path": "2152 3356 174 16509"
    },
    {
      "ts": 1767632551.816961,
      "type": "A",
      "peer_as": 7018,
      "as_path": "7018 6453 16509"
    },
    {
      "ts": 1767632552.018194,
      "type": "A",
      "peer_as": 7018,
      "as_path": "7018 1299 16509"
    },
    {
      "ts": 1767632552.222668,
      "type": "A",
      "peer_as": 7018,
      "as_path": "7018 6453 16509"
    },
    {
      "ts": 1767632552.624387,
      "type": "A",
      "peer_as": 7018,
      "as_path": "7018 1299 16509"
    },
    {
      "ts": 1767632555.785636,
      "type": "A",
      "peer_as": 3257,
      "as_path": "3257 1299 16509"
    },
    {
      "ts": 1767632556.904775,
      "type": "A",
      "peer_as": 57866,
      "as_path": "57866 6830 16509"
    },
    {
      "ts": 1767632559.297106,
      "type": "A",
      "peer_as": 2914,
      "as_path": "2914 6453 16509"
    },
    {
      "ts": 1767632562.847018,
      "type": "A",
      "peer_as": 7018,
      "as_path": "7018 6453 16509"
    },
    {
      "ts": 1767632563.048114,
      "type": "A",
      "peer_as": 7018,
      "as_path": "7018 1299 16509"
    },
    {
      "ts": 1767632563.437573,
      "type": "A",
      "peer_as": 3741,
      "as_path": "3741 174 16509"
    },
    {
      "ts": 1767632563.808502,
      "type": "A",
      "peer_as": 3257,
      "as_path": "3257 1299 16509"
    },
    {
      "ts": 1767632564.057807,
      "type": "A",
      "peer_as": 7018,
      "as_path": "7018 6453 16509"
    },
    {
      "ts": 1767632564.173195,
      "type": "A",
      "peer_as": 6939,
      "as_path": "6939 1299 174 16509"
    },
    {
      "ts": 1767632564.240226,
      "type": "A",
      "peer_as": 3257,
      "as_path": "3257 174 16509"
    },
    {
      "ts": 1767632566.156324,
      "type": "A",
      "peer_as": 2152,
      "as_path": "2152 3356 6453 16509"
    },
    {
      "ts": 1767632567.011977,
      "type": "A",
      "peer_as": 2497,
      "as_path": "2497 174 16509"
    },
    {
      "ts": 1767632567.090183,
      "type": "A",
      "peer_as": 2152,
      "as_path": "2152 3356 174 16509"
    },
    {
      "ts": 1767632568.417705,
      "type": "A",
      "peer_as": 293,
      "as_path": "293 6453 16509"
    },
    {
      "ts": 1767632568.814421,
      "type": "A",
      "peer_as": 2914,
      "as_path": "2914 6453 16509"
    },
    {
      "ts": 1767632569.452301,
      "type": "A",
      "peer_as": 2152,
      "as_path": "2152 3356 6453 16509"
    },
    {
      "ts": 1767632570.232897,
      "type": "A",
      "peer_as": 1403,
      "as_path": "1403 1299 174 16509"
    },
    {
      "ts": 1767632570.433408,
      "type": "A",
      "peer_as": 3257,
      "as_path": "3257 1299 16509"
    },
    {
      "ts": 1767632571.752281,
      "type": "A",
      "peer_as": 2152,
      "as_path": "2152 3356 1299 16509"
    },
    {
      "ts": 1767632572.874066,
      "type": "A",
      "peer_as": 20130,
      "as_path": "20130 6939 1299 174 16509"
    },
    {
      "ts": 1767632573.426198,
      "type": "A",
      "peer_as": 3257,
      "as_path": "3257 6453 16509"
    },
    {
      "ts": 1767632573.458256,
      "type": "A",
      "peer_as": 2152,
      "as_path": "2152 3356 174 16509"
    },
    {
      "ts": 1767632573.495579,
      "type": "A",
      "peer_as": 22652,
      "as_path": "22652 1299 174 16509"
    },
    {
      "ts": 1767632573.783232,
      "type": "A",
      "peer_as": 22652,
      "as_path": "22652 174 1299 16509"
    },
    {
      "ts": 1767632575.326132,
      "type": "A",
      "peer_as": 22652,
      "as_path": "22652 174 1299 16509"
    },
    {
      "ts": 1767632575.539125,
      "type": "A",
      "peer_as": 3257,
      "as_path": "3257 6453 16509"
    },
    {
      "ts": 1767632586.038299,
      "type": "A",
      "peer_as": 57866,
      "as_path": "57866 6830 16509"
    },
    {
      "ts": 1767632590.513575,
      "type": "A",
      "peer_as": 7018,
      "as_path": "7018 174 16509"
    },
    {
      "ts": 1767632591.126793,
      "type": "A",
      "peer_as": 57866,
      "as_path": "57866 5511 174 16509"
    },
    {
      "ts": 1767632592.254076,
      "type": "A",
      "peer_as": 37100,
      "as_path": "37100 6762 6453 16509"
    },
    {
      "ts": 1767632592.283102,
      "type": "A",
      "peer_as": 2914,
      "as_path": "2914 174 16509"
    },
    {
      "ts": 1767632592.372109,
      "type": "A",
      "peer_as": 3257,
      "as_path": "3257 174 16509"
    },
    {
      "ts": 1767632592.524065,
      "type": "A",
      "peer_as": 37100,
      "as_path": "37100 3257 174 16509"
    },
    {
      "ts": 1767632594.758831,
      "type": "A",
      "peer_as": 3257,
      "as_path": "3257 174 16509"
    },
    {
      "ts": 1767632594.885923,
      "type": "W",
      "peer_as": 3549,
      "as_path": ""
    },
    {
      "ts": 1767632594.991588,
      "type": "W",
      "peer_as": 7018,
      "as_path": ""
    },
    {
      "ts": 1767632595.161267,
      "type": "W",
      "peer_as": 3257,
      "as_path": ""
    },
    {
      "ts": 1767632595.66628,
      "type": "A",
      "peer_as": 37100,
      "as_path": "37100 6453 174 16509"
    },
    {
      "ts": 1767632595.852791,
      "type": "W",
      "peer_as": 2152,
      "as_path": ""
    },
    {
      "ts": 1767632596.546866,
      "type": "W",
      "peer_as": 2914,
      "as_path": ""
    },
    {
      "ts": 1767632597.889784,
      "type": "A",
      "peer_as": 2497,
      "as_path": "2497 174 1299 16509"
    },
    {
      "ts": 1767632598.029577,
      "type": "A",
      "peer_as": 57866,
      "as_path": "57866 1299 174 16509"
    },
    {
      "ts": 1767632599.348788,
      "type": "A",
      "peer_as": 2152,
      "as_path": "2152 3356 174 16509"
    },
    {
      "ts": 1767632599.781652,
      "type": "A",
      "peer_as": 57866,
      "as_path": "57866 6453 174 16509"
    },
    {
      "ts": 1767632599.90893,
      "type": "W",
      "peer_as": 2152,
      "as_path": ""
    },
    {
      "ts": 1767632600.716971,
      "type": "A",
      "peer_as": 293,
      "as_path": "293 3356 174 16509"
    },
    {
      "ts": 1767632600.982013,
      "type": "A",
      "peer_as": 20130,
      "as_path": "20130 23352 7922 174 16509"
    },
    {
      "ts": 1767632601.102262,
      "type": "W",
      "peer_as": 6939,
      "as_path": ""
    },
    {
      "ts": 1767632601.18666,
      "type": "A",
      "peer_as": 1403,
      "as_path": "1403 6461 6453 16509"
    },
    {
      "ts": 1767632601.258866,
      "type": "A",
      "peer_as": 20130,
      "as_path": "20130 23352 174 1299 16509"
    },
    {
      "ts": 1767632615.308111,
      "type": "A",
      "peer_as": 1403,
      "as_path": "1403 6461 174 16509"
    },
    {
      "ts": 1767632616.883546,
      "type": "W",
      "peer_as": 57866,
      "as_path": ""
    },
    {
      "ts": 1767632622.193105,
      "type": "A",
      "peer_as": 37100,
      "as_path": "37100 174 1299 16509"
    }
  ],
  "conclusion": "\u8be5\u524d\u7f00\u53d1\u751f\u4e86\u4e00\u8d77\u8def\u7531\u632f\u8361\u4e8b\u4ef6\u3002\u8def\u7531\u632f\u8361: 21W/96A\u3002\u6301\u7eed19\u5206\u949f\uff0c\u6d89\u53ca16\u4e2a\u5bf9\u7b49\u4f53\u64a4\u56de\u3002"
}