{
  "prefix": "79.182.7.0/24",
  "event_type": "D",
  "type_name": "\u6c38\u4e45\u6d88\u5931",
  "origin_as": 0,
  "start_time": 1767636290.217724,
  "end_time": 1767636382.906404,
  "duration_sec": 92.68867993354797,
  "duration_str": "2\u5206\u949f",
  "total_peers": 18,
  "max_withdrawn": 18,
  "total_w": 23,
  "total_a": 0,
  "close_reason": "\u8d85\u65f6, 18\u4e2a\u5bf9\u7b49\u4f53\u672a\u6062\u590d",
  "w_peers": [
    293,
    1403,
    2152,
    2497,
    2914,
    3130,
    3257,
    3303,
    3549,
    3741,
    6939,
    7018,
    20130,
    22652,
    37100,
    49788,
    57463,
    57866
  ],
  "a_peers": [],
  "w_count": 23,
  "a_count": 0,
  "withdrawal_spread_sec": 92.68867993354797,
  "recovery_spread_sec": 0.0,
  "topology": [],
  "updates": [
    {
      "ts": 1767636290.217724,
      "type": "W",
      "peer_as": 57463,
      "as_path": ""
    },
    {
      "ts": 1767636290.334711,
      "type": "W",
      "peer_as": 3257,
      "as_path": ""
    },
    {
      "ts": 1767636321.787648,
      "type": "W",
      "peer_as": 7018,
      "as_path": ""
    },
    {
      "ts": 1767636321.791626,
      "type": "W",
      "peer_as": 2152,
      "as_path": ""
    },
    {
      "ts": 1767636321.794695,
      "type": "W",
      "peer_as": 2152,
      "as_path": ""
    },
    {
      "ts": 1767636321.800834,
      "type": "W",
      "peer_as": 3257,
      "as_path": ""
    },
    {
      "ts": 1767636322.145756,
      "type": "W",
      "peer_as": 6939,
      "as_path": ""
    },
    {
      "ts": 1767636326.244445,
      "type": "W",
      "peer_as": 3130,
      "as_path": ""
    },
    {
      "ts": 1767636326.734189,
      "type": "W",
      "peer_as": 3549,
      "as_path": ""
    },
    {
      "ts": 1767636328.077475,
      "type": "W",
      "peer_as": 22652,
      "as_path": ""
    },
    {
      "ts": 1767636338.113519,
      "type": "W",
      "peer_as": 49788,
      "as_path": ""
    },
    {
      "ts": 1767636339.157949,
      "type": "W",
      "peer_as": 1403,
      "as_path": ""
    },
    {
      "ts": 1767636342.781108,
      "type": "W",
      "peer_as": 22652,
      "as_path": ""
    },
    {
      "ts": 1767636352.470575,
      "type": "W",
      "peer_as": 1403,
      "as_path": ""
    },
    {
      "ts": 1767636352.592322,
      "type": "W",
      "peer_as": 2914,
      "as_path": ""
    },
    {
      "ts": 1767636352.978226,
      "type": "W",
      "peer_as": 37100,
      "as_path": ""
    },
    {
      "ts": 1767636353.00202,
      "type": "W",
      "peer_as": 20130,
      "as_path": ""
    },
    {
      "ts": 1767636355.423545,
      "type": "W",
      "peer_as": 3303,
      "as_path": ""
    },
    {
      "ts": 1767636360.788212,
      "type": "W",
      "peer_as": 293,
      "as_path": ""
    },
    {
      "ts": 1767636368.787404,
      "type": "W",
      "peer_as": 3741,
      "as_path": ""
    },
    {
      "ts": 1767636374.101764,
      "type": "W",
      "peer_as": 57866,
      "as_path": ""
    },
    {
      "ts": 1767636376.597022,
      "type": "W",
      "peer_as": 2497,
      "as_path": ""
    },
    {
      "ts": 1767636382.906404,
      "type": "W",
      "peer_as": 3130,
      "as_path": ""
    }
  ],
  "topo_analysis": "",
  "conclusion": "\u8be5\u524d\u7f00\u53d1\u751f\u4e86\u4e00\u8d77\u6c38\u4e45\u6d88\u5931\u4e8b\u4ef6\u3002\u8d85\u65f6, 18\u4e2a\u5bf9\u7b49\u4f53\u672a\u6062\u590d\u3002\u6301\u7eed2\u5206\u949f\uff0c\u6d89\u53ca18\u4e2a\u5bf9\u7b49\u4f53\u64a4\u56de\uff0c0\u4e2a\u6062\u590d\u3002"
}