{
  "prefix": "177.126.71.0/24",
  "event_type": "C",
  "type_name": "\u8def\u7531\u632f\u8361",
  "origin_as": 0,
  "start_time": 1767227559.485969,
  "end_time": 1767311785.305504,
  "duration_sec": 84225.81953501701,
  "duration_str": "23.4\u5c0f\u65f6",
  "total_peers": 17,
  "max_withdrawn": 17,
  "total_w": 477,
  "total_a": 0,
  "close_reason": "\u8def\u7531\u632f\u8361: 477W/0A",
  "w_peers": [
    293,
    1403,
    2152,
    2497,
    2914,
    3130,
    3257,
    3303,
    3549,
    3741,
    6939,
    7018,
    20130,
    22652,
    37100,
    49788,
    57866
  ],
  "a_peers": [],
  "w_count": 477,
  "a_count": 0,
  "withdrawal_spread_sec": 84225.81953501701,
  "recovery_spread_sec": 0.0,
  "topology": [],
  "updates": [
    {
      "ts": 1767227559.485969,
      "type": "W",
      "peer_as": 7018,
      "as_path": ""
    },
    {
      "ts": 1767227585.778792,
      "type": "W",
      "peer_as": 3303,
      "as_path": ""
    },
    {
      "ts": 1767228528.263921,
      "type": "W",
      "peer_as": 7018,
      "as_path": ""
    },
    {
      "ts": 1767228529.060884,
      "type": "W",
      "peer_as": 6939,
      "as_path": ""
    },
    {
      "ts": 1767228537.783128,
      "type": "W",
      "peer_as": 2914,
      "as_path": ""
    },
    {
      "ts": 1767228540.059881,
      "type": "W",
      "peer_as": 2152,
      "as_path": ""
    },
    {
      "ts": 1767228542.156517,
      "type": "W",
      "peer_as": 3257,
      "as_path": ""
    },
    {
      "ts": 1767228544.271019,
      "type": "W",
      "peer_as": 3130,
      "as_path": ""
    },
    {
      "ts": 1767228544.872336,
      "type": "W",
      "peer_as": 3257,
      "as_path": ""
    },
    {
      "ts": 1767229364.005646,
      "type": "W",
      "peer_as": 6939,
      "as_path": ""
    },
    {
      "ts": 1767231995.675589,
      "type": "W",
      "peer_as": 6939,
      "as_path": ""
    },
    {
      "ts": 1767232058.871991,
      "type": "W",
      "peer_as": 7018,
      "as_path": ""
    },
    {
      "ts": 1767232286.941558,
      "type": "W",
      "peer_as": 3303,
      "as_path": ""
    },
    {
      "ts": 1767232338.678829,
      "type": "W",
      "peer_as": 7018,
      "as_path": ""
    },
    {
      "ts": 1767232355.083185,
      "type": "W",
      "peer_as": 6939,
      "as_path": ""
    },
    {
      "ts": 1767232359.545383,
      "type": "W",
      "peer_as": 6939,
      "as_path": ""
    },
    {
      "ts": 1767232364.209358,
      "type": "W",
      "peer_as": 7018,
      "as_path": ""
    },
    {
      "ts": 1767232367.010813,
      "type": "W",
      "peer_as": 3257,
      "as_path": ""
    },
    {
      "ts": 1767232372.158832,
      "type": "W",
      "peer_as": 2914,
      "as_path": ""
    },
    {
      "ts": 1767232385.103708,
      "type": "W",
      "peer_as": 3130,
      "as_path": ""
    },
    {
      "ts": 1767232385.868702,
      "type": "W",
      "peer_as": 3741,
      "as_path": ""
    },
    {
      "ts": 1767232391.71959,
      "type": "W",
      "peer_as": 49788,
      "as_path": ""
    },
    {
      "ts": 1767232393.861964,
      "type": "W",
      "peer_as": 3549,
      "as_path": ""
    },
    {
      "ts": 1767232394.052339,
      "type": "W",
      "peer_as": 2152,
      "as_path": ""
    },
    {
      "ts": 1767232395.024011,
      "type": "W",
      "peer_as": 3257,
      "as_path": ""
    },
    {
      "ts": 1767232396.268344,
      "type": "W",
      "peer_as": 6939,
      "as_path": ""
    },
    {
      "ts": 1767232396.633567,
      "type": "W",
      "peer_as": 20130,
      "as_path": ""
    },
    {
      "ts": 1767232406.086779,
      "type": "W",
      "peer_as": 2497,
      "as_path": ""
    },
    {
      "ts": 1767232418.102661,
      "type": "W",
      "peer_as": 37100,
      "as_path": ""
    },
    {
      "ts": 1767232425.188913,
      "type": "W",
      "peer_as": 57866,
      "as_path": ""
    },
    {
      "ts": 1767232426.880819,
      "type": "W",
      "peer_as": 3130,
      "as_path": ""
    },
    {
      "ts": 1767232437.769469,
      "type": "W",
      "peer_as": 293,
      "as_path": ""
    },
    {
      "ts": 1767232445.971769,
      "type": "W",
      "peer_as": 1403,
      "as_path": ""
    },
    {
      "ts": 1767233557.723664,
      "type": "W",
      "peer_as": 7018,
      "as_path": ""
    },
    {
      "ts": 1767234801.519716,
      "type": "W",
      "peer_as": 6939,
      "as_path": ""
    },
    {
      "ts": 1767237266.400205,
      "type": "W",
      "peer_as": 6939,
      "as_path": ""
    },
    {
      "ts": 1767239586.988985,
      "type": "W",
      "peer_as": 7018,
      "as_path": ""
    },
    {
      "ts": 1767239613.544632,
      "type": "W",
      "peer_as": 6939,
      "as_path": ""
    },
    {
      "ts": 1767239629.859086,
      "type": "W",
      "peer_as": 3303,
      "as_path": ""
    },
    {
      "ts": 1767239647.900119,
      "type": "W",
      "peer_as": 3257,
      "as_path": ""
    },
    {
      "ts": 1767239894.152242,
      "type": "W",
      "peer_as": 6939,
      "as_path": ""
    },
    {
      "ts": 1767239895.104608,
      "type": "W",
      "peer_as": 7018,
      "as_path": ""
    },
    {
      "ts": 1767239896.188805,
      "type": "W",
      "peer_as": 6939,
      "as_path": ""
    },
    {
      "ts": 1767239909.197629,
      "type": "W",
      "peer_as": 2914,
      "as_path": ""
    },
    {
      "ts": 1767239915.972464,
      "type": "W",
      "peer_as": 3257,
      "as_path": ""
    },
    {
      "ts": 1767239919.160099,
      "type": "W",
      "peer_as": 6939,
      "as_path": ""
    },
    {
      "ts": 1767239922.428102,
      "type": "W",
      "peer_as": 2152,
      "as_path": ""
    },
    {
      "ts": 1767239922.811435,
      "type": "W",
      "peer_as": 49788,
      "as_path": ""
    },
    {
      "ts": 1767239931.255286,
      "type": "W",
      "peer_as": 20130,
      "as_path": ""
    },
    {
      "ts": 1767239941.869111,
      "type": "W",
      "peer_as": 3549,
      "as_path": ""
    },
    {
      "ts": 1767239942.972424,
      "type": "W",
      "peer_as": 3741,
      "as_path": ""
    },
    {
      "ts": 1767239946.891801,
      "type": "W",
      "peer_as": 3130,
      "as_path": ""
    },
    {
      "ts": 1767239947.77034,
      "type": "W",
      "peer_as": 293,
      "as_path": ""
    },
    {
      "ts": 1767239963.655949,
      "type": "W",
      "peer_as": 2497,
      "as_path": ""
    },
    {
      "ts": 1767239980.250813,
      "type": "W",
      "peer_as": 3130,
      "as_path": ""
    },
    {
      "ts": 1767240142.448367,
      "type": "W",
      "peer_as": 37100,
      "as_path": ""
    },
    {
      "ts": 1767240149.018651,
      "type": "W",
      "peer_as": 57866,
      "as_path": ""
    },
    {
      "ts": 1767240195.575577,
      "type": "W",
      "peer_as": 1403,
      "as_path": ""
    },
    {
      "ts": 1767241182.787804,
      "type": "W",
      "peer_as": 3257,
      "as_path": ""
    },
    {
      "ts": 1767241182.792093,
      "type": "W",
      "peer_as": 7018,
      "as_path": ""
    },
    {
      "ts": 1767241210.920098,
      "type": "W",
      "peer_as": 6939,
      "as_path": ""
    },
    {
      "ts": 1767241221.201909,
      "type": "W",
      "peer_as": 7018,
      "as_path": ""
    },
    {
      "ts": 1767241224.618385,
      "type": "W",
      "peer_as": 2914,
      "as_path": ""
    },
    {
      "ts": 1767241237.363304,
      "type": "W",
      "peer_as": 3130,
      "as_path": ""
    },
    {
      "ts": 1767241239.226492,
      "type": "W",
      "peer_as": 3257,
      "as_path": ""
    },
    {
      "ts": 1767241240.269756,
      "type": "W",
      "peer_as": 6939,
      "as_path": ""
    },
    {
      "ts": 1767241244.470684,
      "type": "W",
      "peer_as": 3741,
      "as_path": ""
    },
    {
      "ts": 1767243726.894991,
      "type": "W",
      "peer_as": 7018,
      "as_path": ""
    },
    {
      "ts": 1767245070.127461,
      "type": "W",
      "peer_as": 6939,
      "as_path": ""
    },
    {
      "ts": 1767246388.889487,
      "type": "W",
      "peer_as": 6939,
      "as_path": ""
    },
    {
      "ts": 1767247304.904894,
      "type": "W",
      "peer_as": 7018,
      "as_path": ""
    },
    {
      "ts": 1767247333.24039,
      "type": "W",
      "peer_as": 7018,
      "as_path": ""
    },
    {
      "ts": 1767247574.669175,
      "type": "W",
      "peer_as": 6939,
      "as_path": ""
    },
    {
      "ts": 1767247588.808385,
      "type": "W",
      "peer_as": 7018,
      "as_path": ""
    },
    {
      "ts": 1767247619.192233,
      "type": "W",
      "peer_as": 6939,
      "as_path": ""
    },
    {
      "ts": 1767247619.307071,
      "type": "W",
      "peer_as": 7018,
      "as_path": ""
    },
    {
      "ts": 1767247619.912141,
      "type": "W",
      "peer_as": 2914,
      "as_path": ""
    },
    {
      "ts": 1767247620.968968,
      "type": "W",
      "peer_as": 3257,
      "as_path": ""
    },
    {
      "ts": 1767247641.277905,
      "type": "W",
      "peer_as": 3257,
      "as_path": ""
    },
    {
      "ts": 1767247642.679604,
      "type": "W",
      "peer_as": 6939,
      "as_path": ""
    },
    {
      "ts": 1767247648.419592,
      "type": "W",
      "peer_as": 20130,
      "as_path": ""
    },
    {
      "ts": 1767247649.9284,
      "type": "W",
      "peer_as": 3549,
      "as_path": ""
    },
    {
      "ts": 1767247650.855571,
      "type": "W",
      "peer_as": 2152,
      "as_path": ""
    },
    {
      "ts": 1767247655.019245,
      "type": "W",
      "peer_as": 3741,
      "as_path": ""
    },
    {
      "ts": 1767247659.463434,
      "type": "W",
      "peer_as": 3130,
      "as_path": ""
    },
    {
      "ts": 1767247663.334911,
      "type": "W",
      "peer_as": 49788,
      "as_path": ""
    },
    {
      "ts": 1767247675.488549,
      "type": "W",
      "peer_as": 2497,
      "as_path": ""
    },
    {
      "ts": 1767247693.095564,
      "type": "W",
      "peer_as": 3130,
      "as_path": ""
    },
    {
      "ts": 1767247702.758052,
      "type": "W",
      "peer_as": 293,
      "as_path": ""
    },
    {
      "ts": 1767247726.054918,
      "type": "W",
      "peer_as": 57866,
      "as_path": ""
    },
    {
      "ts": 1767247729.187049,
      "type": "W",
      "peer_as": 37100,
      "as_path": ""
    },
    {
      "ts": 1767247757.565317,
      "type": "W",
      "peer_as": 1403,
      "as_path": ""
    },
    {
      "ts": 1767248888.354177,
      "type": "W",
      "peer_as": 6939,
      "as_path": ""
    },
    {
      "ts": 1767248903.714768,
      "type": "W",
      "peer_as": 3257,
      "as_path": ""
    },
    {
      "ts": 1767248930.166063,
      "type": "W",
      "peer_as": 6939,
      "as_path": ""
    },
    {
      "ts": 1767248935.444808,
      "type": "W",
      "peer_as": 6939,
      "as_path": ""
    },
    {
      "ts": 1767248943.156539,
      "type": "W",
      "peer_as": 7018,
      "as_path": ""
    },
    {
      "ts": 1767248948.511238,
      "type": "W",
      "peer_as": 2914,
      "as_path": ""
    },
    {
      "ts": 1767248953.967354,
      "type": "W",
      "peer_as": 3549,
      "as_path": ""
    },
    {
      "ts": 1767248954.728864,
      "type": "W",
      "peer_as": 2152,
      "as_path": ""
    }
  ],
  "topo_analysis": "",
  "conclusion": "\u8be5\u524d\u7f00\u53d1\u751f\u4e86\u4e00\u8d77\u8def\u7531\u632f\u8361\u4e8b\u4ef6\u3002\u8def\u7531\u632f\u8361: 477W/0A\u3002\u6301\u7eed23.4\u5c0f\u65f6\uff0c\u6d89\u53ca17\u4e2a\u5bf9\u7b49\u4f53\u64a4\u56de\uff0c0\u4e2a\u6062\u590d\u3002"
}