{
  "prefix": "43.174.216.0/24",
  "event_type": "C",
  "type_name": "\u8def\u7531\u632f\u8361",
  "origin_as": 0,
  "start_time": 1767225809.744926,
  "end_time": 1767311979.741885,
  "duration_sec": 86169.99695897102,
  "duration_str": "23.9\u5c0f\u65f6",
  "total_peers": 12,
  "max_withdrawn": 12,
  "total_w": 113,
  "total_a": 0,
  "close_reason": "\u8def\u7531\u632f\u8361: 113W/0A",
  "w_peers": [
    293,
    2152,
    2914,
    3130,
    3257,
    3303,
    3549,
    3741,
    6939,
    7018,
    22652,
    49788
  ],
  "a_peers": [],
  "w_count": 113,
  "a_count": 0,
  "withdrawal_spread_sec": 86169.99695897102,
  "recovery_spread_sec": 0.0,
  "topology": [],
  "updates": [
    {
      "ts": 1767225809.744926,
      "type": "W",
      "peer_as": 22652,
      "as_path": ""
    },
    {
      "ts": 1767226599.770241,
      "type": "W",
      "peer_as": 6939,
      "as_path": ""
    },
    {
      "ts": 1767226647.557417,
      "type": "W",
      "peer_as": 293,
      "as_path": ""
    },
    {
      "ts": 1767228973.387411,
      "type": "W",
      "peer_as": 7018,
      "as_path": ""
    },
    {
      "ts": 1767231378.467606,
      "type": "W",
      "peer_as": 3257,
      "as_path": ""
    },
    {
      "ts": 1767231394.16159,
      "type": "W",
      "peer_as": 7018,
      "as_path": ""
    },
    {
      "ts": 1767231457.473043,
      "type": "W",
      "peer_as": 3303,
      "as_path": ""
    },
    {
      "ts": 1767233787.792314,
      "type": "W",
      "peer_as": 6939,
      "as_path": ""
    },
    {
      "ts": 1767233812.442656,
      "type": "W",
      "peer_as": 7018,
      "as_path": ""
    },
    {
      "ts": 1767233815.969372,
      "type": "W",
      "peer_as": 6939,
      "as_path": ""
    },
    {
      "ts": 1767236196.719257,
      "type": "W",
      "peer_as": 3549,
      "as_path": ""
    },
    {
      "ts": 1767236198.743192,
      "type": "W",
      "peer_as": 7018,
      "as_path": ""
    },
    {
      "ts": 1767236209.105021,
      "type": "W",
      "peer_as": 6939,
      "as_path": ""
    },
    {
      "ts": 1767237047.686439,
      "type": "W",
      "peer_as": 22652,
      "as_path": ""
    },
    {
      "ts": 1767237403.775353,
      "type": "W",
      "peer_as": 3257,
      "as_path": ""
    },
    {
      "ts": 1767238598.702235,
      "type": "W",
      "peer_as": 7018,
      "as_path": ""
    },
    {
      "ts": 1767239798.582245,
      "type": "W",
      "peer_as": 7018,
      "as_path": ""
    },
    {
      "ts": 1767241001.583962,
      "type": "W",
      "peer_as": 3257,
      "as_path": ""
    },
    {
      "ts": 1767242223.06356,
      "type": "W",
      "peer_as": 3549,
      "as_path": ""
    },
    {
      "ts": 1767242224.424298,
      "type": "W",
      "peer_as": 7018,
      "as_path": ""
    },
    {
      "ts": 1767242225.836784,
      "type": "W",
      "peer_as": 2152,
      "as_path": ""
    },
    {
      "ts": 1767242228.327137,
      "type": "W",
      "peer_as": 6939,
      "as_path": ""
    },
    {
      "ts": 1767243408.740346,
      "type": "W",
      "peer_as": 3257,
      "as_path": ""
    },
    {
      "ts": 1767243412.53111,
      "type": "W",
      "peer_as": 7018,
      "as_path": ""
    },
    {
      "ts": 1767243427.900923,
      "type": "W",
      "peer_as": 3130,
      "as_path": ""
    },
    {
      "ts": 1767244608.785908,
      "type": "W",
      "peer_as": 7018,
      "as_path": ""
    },
    {
      "ts": 1767245820.785124,
      "type": "W",
      "peer_as": 3549,
      "as_path": ""
    },
    {
      "ts": 1767245824.193819,
      "type": "W",
      "peer_as": 7018,
      "as_path": ""
    },
    {
      "ts": 1767245834.924926,
      "type": "W",
      "peer_as": 3549,
      "as_path": ""
    },
    {
      "ts": 1767245834.978259,
      "type": "W",
      "peer_as": 2152,
      "as_path": ""
    },
    {
      "ts": 1767248215.941114,
      "type": "W",
      "peer_as": 3549,
      "as_path": ""
    },
    {
      "ts": 1767248218.258996,
      "type": "W",
      "peer_as": 7018,
      "as_path": ""
    },
    {
      "ts": 1767248229.757604,
      "type": "W",
      "peer_as": 2152,
      "as_path": ""
    },
    {
      "ts": 1767250616.178339,
      "type": "W",
      "peer_as": 3549,
      "as_path": ""
    },
    {
      "ts": 1767250619.403143,
      "type": "W",
      "peer_as": 7018,
      "as_path": ""
    },
    {
      "ts": 1767250619.471545,
      "type": "W",
      "peer_as": 2152,
      "as_path": ""
    },
    {
      "ts": 1767250631.812662,
      "type": "W",
      "peer_as": 2152,
      "as_path": ""
    },
    {
      "ts": 1767250640.711367,
      "type": "W",
      "peer_as": 6939,
      "as_path": ""
    },
    {
      "ts": 1767250658.056579,
      "type": "W",
      "peer_as": 3303,
      "as_path": ""
    },
    {
      "ts": 1767251817.580277,
      "type": "W",
      "peer_as": 6939,
      "as_path": ""
    },
    {
      "ts": 1767253028.66921,
      "type": "W",
      "peer_as": 3549,
      "as_path": ""
    },
    {
      "ts": 1767253029.333716,
      "type": "W",
      "peer_as": 3549,
      "as_path": ""
    },
    {
      "ts": 1767253030.40845,
      "type": "W",
      "peer_as": 2152,
      "as_path": ""
    },
    {
      "ts": 1767254236.605184,
      "type": "W",
      "peer_as": 3130,
      "as_path": ""
    },
    {
      "ts": 1767254240.196907,
      "type": "W",
      "peer_as": 7018,
      "as_path": ""
    },
    {
      "ts": 1767254276.947564,
      "type": "W",
      "peer_as": 2914,
      "as_path": ""
    },
    {
      "ts": 1767254280.241127,
      "type": "W",
      "peer_as": 3741,
      "as_path": ""
    },
    {
      "ts": 1767254284.318466,
      "type": "W",
      "peer_as": 3303,
      "as_path": ""
    },
    {
      "ts": 1767257831.43128,
      "type": "W",
      "peer_as": 3257,
      "as_path": ""
    },
    {
      "ts": 1767257831.477294,
      "type": "W",
      "peer_as": 2914,
      "as_path": ""
    },
    {
      "ts": 1767257833.051836,
      "type": "W",
      "peer_as": 3549,
      "as_path": ""
    },
    {
      "ts": 1767257833.68536,
      "type": "W",
      "peer_as": 2152,
      "as_path": ""
    },
    {
      "ts": 1767257833.718459,
      "type": "W",
      "peer_as": 3257,
      "as_path": ""
    },
    {
      "ts": 1767257834.474857,
      "type": "W",
      "peer_as": 7018,
      "as_path": ""
    },
    {
      "ts": 1767257834.536163,
      "type": "W",
      "peer_as": 6939,
      "as_path": ""
    },
    {
      "ts": 1767257834.865067,
      "type": "W",
      "peer_as": 3549,
      "as_path": ""
    },
    {
      "ts": 1767257835.050127,
      "type": "W",
      "peer_as": 2152,
      "as_path": ""
    },
    {
      "ts": 1767259068.601835,
      "type": "W",
      "peer_as": 7018,
      "as_path": ""
    },
    {
      "ts": 1767259072.835314,
      "type": "W",
      "peer_as": 3130,
      "as_path": ""
    },
    {
      "ts": 1767259075.573774,
      "type": "W",
      "peer_as": 2914,
      "as_path": ""
    },
    {
      "ts": 1767259077.077722,
      "type": "W",
      "peer_as": 3303,
      "as_path": ""
    },
    {
      "ts": 1767259109.165904,
      "type": "W",
      "peer_as": 3741,
      "as_path": ""
    },
    {
      "ts": 1767266296.484646,
      "type": "W",
      "peer_as": 3303,
      "as_path": ""
    },
    {
      "ts": 1767267481.126768,
      "type": "W",
      "peer_as": 3549,
      "as_path": ""
    },
    {
      "ts": 1767267482.047328,
      "type": "W",
      "peer_as": 49788,
      "as_path": ""
    },
    {
      "ts": 1767267482.12915,
      "type": "W",
      "peer_as": 7018,
      "as_path": ""
    },
    {
      "ts": 1767267482.818599,
      "type": "W",
      "peer_as": 2152,
      "as_path": ""
    },
    {
      "ts": 1767267494.044731,
      "type": "W",
      "peer_as": 3303,
      "as_path": ""
    },
    {
      "ts": 1767267519.092886,
      "type": "W",
      "peer_as": 3741,
      "as_path": ""
    },
    {
      "ts": 1767268199.767604,
      "type": "W",
      "peer_as": 22652,
      "as_path": ""
    },
    {
      "ts": 1767278321.153622,
      "type": "W",
      "peer_as": 6939,
      "as_path": ""
    },
    {
      "ts": 1767283133.815265,
      "type": "W",
      "peer_as": 6939,
      "as_path": ""
    },
    {
      "ts": 1767287947.790875,
      "type": "W",
      "peer_as": 6939,
      "as_path": ""
    },
    {
      "ts": 1767290321.140145,
      "type": "W",
      "peer_as": 3549,
      "as_path": ""
    },
    {
      "ts": 1767290324.47658,
      "type": "W",
      "peer_as": 7018,
      "as_path": ""
    },
    {
      "ts": 1767290326.078765,
      "type": "W",
      "peer_as": 2152,
      "as_path": ""
    },
    {
      "ts": 1767291606.771571,
      "type": "W",
      "peer_as": 22652,
      "as_path": ""
    },
    {
      "ts": 1767292733.261819,
      "type": "W",
      "peer_as": 3549,
      "as_path": ""
    },
    {
      "ts": 1767292734.486859,
      "type": "W",
      "peer_as": 2152,
      "as_path": ""
    },
    {
      "ts": 1767292734.560843,
      "type": "W",
      "peer_as": 7018,
      "as_path": ""
    },
    {
      "ts": 1767293935.696445,
      "type": "W",
      "peer_as": 7018,
      "as_path": ""
    },
    {
      "ts": 1767297537.707449,
      "type": "W",
      "peer_as": 3549,
      "as_path": ""
    },
    {
      "ts": 1767297539.561369,
      "type": "W",
      "peer_as": 7018,
      "as_path": ""
    },
    {
      "ts": 1767297540.28572,
      "type": "W",
      "peer_as": 2152,
      "as_path": ""
    },
    {
      "ts": 1767302354.160886,
      "type": "W",
      "peer_as": 3257,
      "as_path": ""
    },
    {
      "ts": 1767305956.801075,
      "type": "W",
      "peer_as": 3549,
      "as_path": ""
    },
    {
      "ts": 1767305958.089043,
      "type": "W",
      "peer_as": 6939,
      "as_path": ""
    },
    {
      "ts": 1767305958.102779,
      "type": "W",
      "peer_as": 7018,
      "as_path": ""
    },
    {
      "ts": 1767305958.832873,
      "type": "W",
      "peer_as": 2152,
      "as_path": ""
    },
    {
      "ts": 1767305960.776198,
      "type": "W",
      "peer_as": 2914,
      "as_path": ""
    },
    {
      "ts": 1767305966.621732,
      "type": "W",
      "peer_as": 6939,
      "as_path": ""
    },
    {
      "ts": 1767305967.690417,
      "type": "W",
      "peer_as": 2152,
      "as_path": ""
    },
    {
      "ts": 1767305994.377579,
      "type": "W",
      "peer_as": 3130,
      "as_path": ""
    },
    {
      "ts": 1767306001.436128,
      "type": "W",
      "peer_as": 3741,
      "as_path": ""
    },
    {
      "ts": 1767308357.104578,
      "type": "W",
      "peer_as": 3549,
      "as_path": ""
    },
    {
      "ts": 1767308358.049674,
      "type": "W",
      "peer_as": 2914,
      "as_path": ""
    },
    {
      "ts": 1767308358.610962,
      "type": "W",
      "peer_as": 2152,
      "as_path": ""
    },
    {
      "ts": 1767308359.056815,
      "type": "W",
      "peer_as": 3257,
      "as_path": ""
    },
    {
      "ts": 1767308359.414335,
      "type": "W",
      "peer_as": 6939,
      "as_path": ""
    },
    {
      "ts": 1767308360.387912,
      "type": "W",
      "peer_as": 7018,
      "as_path": ""
    }
  ],
  "topo_analysis": "",
  "conclusion": "\u8be5\u524d\u7f00\u53d1\u751f\u4e86\u4e00\u8d77\u8def\u7531\u632f\u8361\u4e8b\u4ef6\u3002\u8def\u7531\u632f\u8361: 113W/0A\u3002\u6301\u7eed23.9\u5c0f\u65f6\uff0c\u6d89\u53ca12\u4e2a\u5bf9\u7b49\u4f53\u64a4\u56de\uff0c0\u4e2a\u6062\u590d\u3002"
}