{
  "prefix": "158.116.198.0/24",
  "event_type": "C",
  "type_name": "\u8def\u7531\u632f\u8361",
  "origin_as": 0,
  "start_time": 1767225693.484255,
  "end_time": 1767311881.318623,
  "duration_sec": 86187.8343679905,
  "duration_str": "23.9\u5c0f\u65f6",
  "total_peers": 1,
  "max_withdrawn": 1,
  "total_w": 390,
  "total_a": 0,
  "close_reason": "\u8def\u7531\u632f\u8361: 390W/0A",
  "w_peers": [
    3130
  ],
  "a_peers": [],
  "w_count": 390,
  "a_count": 0,
  "withdrawal_spread_sec": 86187.8343679905,
  "recovery_spread_sec": 0.0,
  "topology": [],
  "updates": [
    {
      "ts": 1767225693.484255,
      "type": "W",
      "peer_as": 3130,
      "as_path": ""
    },
    {
      "ts": 1767225903.550659,
      "type": "W",
      "peer_as": 3130,
      "as_path": ""
    },
    {
      "ts": 1767226143.601443,
      "type": "W",
      "peer_as": 3130,
      "as_path": ""
    },
    {
      "ts": 1767226353.647903,
      "type": "W",
      "peer_as": 3130,
      "as_path": ""
    },
    {
      "ts": 1767226593.70137,
      "type": "W",
      "peer_as": 3130,
      "as_path": ""
    },
    {
      "ts": 1767226803.755414,
      "type": "W",
      "peer_as": 3130,
      "as_path": ""
    },
    {
      "ts": 1767227013.794925,
      "type": "W",
      "peer_as": 3130,
      "as_path": ""
    },
    {
      "ts": 1767227223.830192,
      "type": "W",
      "peer_as": 3130,
      "as_path": ""
    },
    {
      "ts": 1767227463.884593,
      "type": "W",
      "peer_as": 3130,
      "as_path": ""
    },
    {
      "ts": 1767227674.086926,
      "type": "W",
      "peer_as": 3130,
      "as_path": ""
    },
    {
      "ts": 1767227884.127222,
      "type": "W",
      "peer_as": 3130,
      "as_path": ""
    },
    {
      "ts": 1767228094.158967,
      "type": "W",
      "peer_as": 3130,
      "as_path": ""
    },
    {
      "ts": 1767228334.229474,
      "type": "W",
      "peer_as": 3130,
      "as_path": ""
    },
    {
      "ts": 1767228544.278233,
      "type": "W",
      "peer_as": 3130,
      "as_path": ""
    },
    {
      "ts": 1767228754.310846,
      "type": "W",
      "peer_as": 3130,
      "as_path": ""
    },
    {
      "ts": 1767228964.388392,
      "type": "W",
      "peer_as": 3130,
      "as_path": ""
    },
    {
      "ts": 1767229204.477847,
      "type": "W",
      "peer_as": 3130,
      "as_path": ""
    },
    {
      "ts": 1767229414.527787,
      "type": "W",
      "peer_as": 3130,
      "as_path": ""
    },
    {
      "ts": 1767229624.577179,
      "type": "W",
      "peer_as": 3130,
      "as_path": ""
    },
    {
      "ts": 1767229834.612727,
      "type": "W",
      "peer_as": 3130,
      "as_path": ""
    },
    {
      "ts": 1767230074.664549,
      "type": "W",
      "peer_as": 3130,
      "as_path": ""
    },
    {
      "ts": 1767230284.706821,
      "type": "W",
      "peer_as": 3130,
      "as_path": ""
    },
    {
      "ts": 1767230494.745145,
      "type": "W",
      "peer_as": 3130,
      "as_path": ""
    },
    {
      "ts": 1767230704.784407,
      "type": "W",
      "peer_as": 3130,
      "as_path": ""
    },
    {
      "ts": 1767230944.835688,
      "type": "W",
      "peer_as": 3130,
      "as_path": ""
    },
    {
      "ts": 1767231154.878482,
      "type": "W",
      "peer_as": 3130,
      "as_path": ""
    },
    {
      "ts": 1767231364.927807,
      "type": "W",
      "peer_as": 3130,
      "as_path": ""
    },
    {
      "ts": 1767231604.975063,
      "type": "W",
      "peer_as": 3130,
      "as_path": ""
    },
    {
      "ts": 1767231815.01739,
      "type": "W",
      "peer_as": 3130,
      "as_path": ""
    },
    {
      "ts": 1767232025.053452,
      "type": "W",
      "peer_as": 3130,
      "as_path": ""
    },
    {
      "ts": 1767232235.087991,
      "type": "W",
      "peer_as": 3130,
      "as_path": ""
    },
    {
      "ts": 1767232445.125117,
      "type": "W",
      "peer_as": 3130,
      "as_path": ""
    },
    {
      "ts": 1767232685.195792,
      "type": "W",
      "peer_as": 3130,
      "as_path": ""
    },
    {
      "ts": 1767232895.238516,
      "type": "W",
      "peer_as": 3130,
      "as_path": ""
    },
    {
      "ts": 1767233345.388413,
      "type": "W",
      "peer_as": 3130,
      "as_path": ""
    },
    {
      "ts": 1767233585.433299,
      "type": "W",
      "peer_as": 3130,
      "as_path": ""
    },
    {
      "ts": 1767233795.487442,
      "type": "W",
      "peer_as": 3130,
      "as_path": ""
    },
    {
      "ts": 1767234005.549832,
      "type": "W",
      "peer_as": 3130,
      "as_path": ""
    },
    {
      "ts": 1767234215.596996,
      "type": "W",
      "peer_as": 3130,
      "as_path": ""
    },
    {
      "ts": 1767234425.640019,
      "type": "W",
      "peer_as": 3130,
      "as_path": ""
    },
    {
      "ts": 1767234665.691918,
      "type": "W",
      "peer_as": 3130,
      "as_path": ""
    },
    {
      "ts": 1767234875.774209,
      "type": "W",
      "peer_as": 3130,
      "as_path": ""
    },
    {
      "ts": 1767235085.803987,
      "type": "W",
      "peer_as": 3130,
      "as_path": ""
    },
    {
      "ts": 1767235325.855206,
      "type": "W",
      "peer_as": 3130,
      "as_path": ""
    },
    {
      "ts": 1767235535.892534,
      "type": "W",
      "peer_as": 3130,
      "as_path": ""
    },
    {
      "ts": 1767235745.942435,
      "type": "W",
      "peer_as": 3130,
      "as_path": ""
    },
    {
      "ts": 1767235955.999621,
      "type": "W",
      "peer_as": 3130,
      "as_path": ""
    },
    {
      "ts": 1767236196.030354,
      "type": "W",
      "peer_as": 3130,
      "as_path": ""
    },
    {
      "ts": 1767236406.088588,
      "type": "W",
      "peer_as": 3130,
      "as_path": ""
    },
    {
      "ts": 1767236616.131304,
      "type": "W",
      "peer_as": 3130,
      "as_path": ""
    },
    {
      "ts": 1767236826.15761,
      "type": "W",
      "peer_as": 3130,
      "as_path": ""
    },
    {
      "ts": 1767237066.212409,
      "type": "W",
      "peer_as": 3130,
      "as_path": ""
    },
    {
      "ts": 1767237276.273274,
      "type": "W",
      "peer_as": 3130,
      "as_path": ""
    },
    {
      "ts": 1767237486.322677,
      "type": "W",
      "peer_as": 3130,
      "as_path": ""
    },
    {
      "ts": 1767237696.355458,
      "type": "W",
      "peer_as": 3130,
      "as_path": ""
    },
    {
      "ts": 1767237936.404008,
      "type": "W",
      "peer_as": 3130,
      "as_path": ""
    },
    {
      "ts": 1767238146.469472,
      "type": "W",
      "peer_as": 3130,
      "as_path": ""
    },
    {
      "ts": 1767238356.526773,
      "type": "W",
      "peer_as": 3130,
      "as_path": ""
    },
    {
      "ts": 1767238566.617402,
      "type": "W",
      "peer_as": 3130,
      "as_path": ""
    },
    {
      "ts": 1767238776.657356,
      "type": "W",
      "peer_as": 3130,
      "as_path": ""
    },
    {
      "ts": 1767239016.707708,
      "type": "W",
      "peer_as": 3130,
      "as_path": ""
    },
    {
      "ts": 1767239226.751942,
      "type": "W",
      "peer_as": 3130,
      "as_path": ""
    },
    {
      "ts": 1767239466.798115,
      "type": "W",
      "peer_as": 3130,
      "as_path": ""
    },
    {
      "ts": 1767239676.850157,
      "type": "W",
      "peer_as": 3130,
      "as_path": ""
    },
    {
      "ts": 1767239886.88726,
      "type": "W",
      "peer_as": 3130,
      "as_path": ""
    },
    {
      "ts": 1767240096.927914,
      "type": "W",
      "peer_as": 3130,
      "as_path": ""
    },
    {
      "ts": 1767240336.96591,
      "type": "W",
      "peer_as": 3130,
      "as_path": ""
    },
    {
      "ts": 1767240547.226073,
      "type": "W",
      "peer_as": 3130,
      "as_path": ""
    },
    {
      "ts": 1767240787.265073,
      "type": "W",
      "peer_as": 3130,
      "as_path": ""
    },
    {
      "ts": 1767240967.305939,
      "type": "W",
      "peer_as": 3130,
      "as_path": ""
    },
    {
      "ts": 1767241207.355933,
      "type": "W",
      "peer_as": 3130,
      "as_path": ""
    },
    {
      "ts": 1767241417.39961,
      "type": "W",
      "peer_as": 3130,
      "as_path": ""
    },
    {
      "ts": 1767241627.447115,
      "type": "W",
      "peer_as": 3130,
      "as_path": ""
    },
    {
      "ts": 1767241837.49821,
      "type": "W",
      "peer_as": 3130,
      "as_path": ""
    },
    {
      "ts": 1767242077.563693,
      "type": "W",
      "peer_as": 3130,
      "as_path": ""
    },
    {
      "ts": 1767242287.673596,
      "type": "W",
      "peer_as": 3130,
      "as_path": ""
    },
    {
      "ts": 1767242497.708692,
      "type": "W",
      "peer_as": 3130,
      "as_path": ""
    },
    {
      "ts": 1767242707.751412,
      "type": "W",
      "peer_as": 3130,
      "as_path": ""
    },
    {
      "ts": 1767242917.798462,
      "type": "W",
      "peer_as": 3130,
      "as_path": ""
    },
    {
      "ts": 1767243157.85603,
      "type": "W",
      "peer_as": 3130,
      "as_path": ""
    },
    {
      "ts": 1767243367.888901,
      "type": "W",
      "peer_as": 3130,
      "as_path": ""
    },
    {
      "ts": 1767243577.92746,
      "type": "W",
      "peer_as": 3130,
      "as_path": ""
    },
    {
      "ts": 1767243817.992579,
      "type": "W",
      "peer_as": 3130,
      "as_path": ""
    },
    {
      "ts": 1767244028.026691,
      "type": "W",
      "peer_as": 3130,
      "as_path": ""
    },
    {
      "ts": 1767244238.093207,
      "type": "W",
      "peer_as": 3130,
      "as_path": ""
    },
    {
      "ts": 1767244478.157067,
      "type": "W",
      "peer_as": 3130,
      "as_path": ""
    },
    {
      "ts": 1767244688.204253,
      "type": "W",
      "peer_as": 3130,
      "as_path": ""
    },
    {
      "ts": 1767244898.504735,
      "type": "W",
      "peer_as": 3130,
      "as_path": ""
    },
    {
      "ts": 1767245138.545582,
      "type": "W",
      "peer_as": 3130,
      "as_path": ""
    },
    {
      "ts": 1767245348.636969,
      "type": "W",
      "peer_as": 3130,
      "as_path": ""
    },
    {
      "ts": 1767245558.67548,
      "type": "W",
      "peer_as": 3130,
      "as_path": ""
    },
    {
      "ts": 1767245768.92935,
      "type": "W",
      "peer_as": 3130,
      "as_path": ""
    },
    {
      "ts": 1767246008.975567,
      "type": "W",
      "peer_as": 3130,
      "as_path": ""
    },
    {
      "ts": 1767246219.038726,
      "type": "W",
      "peer_as": 3130,
      "as_path": ""
    },
    {
      "ts": 1767246429.124717,
      "type": "W",
      "peer_as": 3130,
      "as_path": ""
    },
    {
      "ts": 1767246639.164497,
      "type": "W",
      "peer_as": 3130,
      "as_path": ""
    },
    {
      "ts": 1767246849.200163,
      "type": "W",
      "peer_as": 3130,
      "as_path": ""
    },
    {
      "ts": 1767247089.251966,
      "type": "W",
      "peer_as": 3130,
      "as_path": ""
    },
    {
      "ts": 1767247299.289458,
      "type": "W",
      "peer_as": 3130,
      "as_path": ""
    },
    {
      "ts": 1767247749.50387,
      "type": "W",
      "peer_as": 3130,
      "as_path": ""
    }
  ],
  "topo_analysis": "",
  "conclusion": "\u8be5\u524d\u7f00\u53d1\u751f\u4e86\u4e00\u8d77\u8def\u7531\u632f\u8361\u4e8b\u4ef6\u3002\u8def\u7531\u632f\u8361: 390W/0A\u3002\u6301\u7eed23.9\u5c0f\u65f6\uff0c\u6d89\u53ca1\u4e2a\u5bf9\u7b49\u4f53\u64a4\u56de\uff0c0\u4e2a\u6062\u590d\u3002"
}