{
  "prefix": "131.196.122.0/24",
  "event_type": "D",
  "type_name": "\u6c38\u4e45\u6d88\u5931",
  "origin_as": 0,
  "start_time": 1767234704.870792,
  "end_time": 1767235082.892574,
  "duration_sec": 378.0217821598053,
  "duration_str": "6\u5206\u949f",
  "total_peers": 17,
  "max_withdrawn": 17,
  "total_w": 24,
  "total_a": 0,
  "close_reason": "\u8d85\u65f6, 17\u4e2a\u5bf9\u7b49\u4f53\u672a\u6062\u590d",
  "w_peers": [
    293,
    1403,
    2152,
    2497,
    2914,
    3130,
    3257,
    3303,
    3549,
    3741,
    6939,
    7018,
    20130,
    22652,
    37100,
    49788,
    57866
  ],
  "a_peers": [],
  "w_count": 24,
  "a_count": 0,
  "withdrawal_spread_sec": 378.0217821598053,
  "recovery_spread_sec": 0.0,
  "topology": [],
  "updates": [
    {
      "ts": 1767234704.870792,
      "type": "W",
      "peer_as": 49788,
      "as_path": ""
    },
    {
      "ts": 1767234730.834992,
      "type": "W",
      "peer_as": 7018,
      "as_path": ""
    },
    {
      "ts": 1767234734.320307,
      "type": "W",
      "peer_as": 3257,
      "as_path": ""
    },
    {
      "ts": 1767234744.868066,
      "type": "W",
      "peer_as": 3303,
      "as_path": ""
    },
    {
      "ts": 1767234745.834758,
      "type": "W",
      "peer_as": 6939,
      "as_path": ""
    },
    {
      "ts": 1767234746.467879,
      "type": "W",
      "peer_as": 6939,
      "as_path": ""
    },
    {
      "ts": 1767234760.703033,
      "type": "W",
      "peer_as": 3257,
      "as_path": ""
    },
    {
      "ts": 1767234770.475369,
      "type": "W",
      "peer_as": 7018,
      "as_path": ""
    },
    {
      "ts": 1767234771.197769,
      "type": "W",
      "peer_as": 2152,
      "as_path": ""
    },
    {
      "ts": 1767234771.301243,
      "type": "W",
      "peer_as": 3549,
      "as_path": ""
    },
    {
      "ts": 1767234772.517769,
      "type": "W",
      "peer_as": 2914,
      "as_path": ""
    },
    {
      "ts": 1767234773.831824,
      "type": "W",
      "peer_as": 6939,
      "as_path": ""
    },
    {
      "ts": 1767234785.742627,
      "type": "W",
      "peer_as": 3130,
      "as_path": ""
    },
    {
      "ts": 1767234786.28968,
      "type": "W",
      "peer_as": 37100,
      "as_path": ""
    },
    {
      "ts": 1767234791.924441,
      "type": "W",
      "peer_as": 49788,
      "as_path": ""
    },
    {
      "ts": 1767234802.22266,
      "type": "W",
      "peer_as": 2497,
      "as_path": ""
    },
    {
      "ts": 1767234819.109592,
      "type": "W",
      "peer_as": 3741,
      "as_path": ""
    },
    {
      "ts": 1767234819.878229,
      "type": "W",
      "peer_as": 293,
      "as_path": ""
    },
    {
      "ts": 1767234824.866126,
      "type": "W",
      "peer_as": 3130,
      "as_path": ""
    },
    {
      "ts": 1767234832.268843,
      "type": "W",
      "peer_as": 20130,
      "as_path": ""
    },
    {
      "ts": 1767234857.116732,
      "type": "W",
      "peer_as": 57866,
      "as_path": ""
    },
    {
      "ts": 1767234879.59074,
      "type": "W",
      "peer_as": 1403,
      "as_path": ""
    },
    {
      "ts": 1767234883.480125,
      "type": "W",
      "peer_as": 37100,
      "as_path": ""
    },
    {
      "ts": 1767235082.892574,
      "type": "W",
      "peer_as": 22652,
      "as_path": ""
    }
  ],
  "topo_analysis": "",
  "conclusion": "\u8be5\u524d\u7f00\u53d1\u751f\u4e86\u4e00\u8d77\u6c38\u4e45\u6d88\u5931\u4e8b\u4ef6\u3002\u8d85\u65f6, 17\u4e2a\u5bf9\u7b49\u4f53\u672a\u6062\u590d\u3002\u6301\u7eed6\u5206\u949f\uff0c\u6d89\u53ca17\u4e2a\u5bf9\u7b49\u4f53\u64a4\u56de\uff0c0\u4e2a\u6062\u590d\u3002"
}